vgraphdb/TorusE.py
vgraphdb/__init__.py
vgraphdb/embed.py
vgraphdb/models.py
vgraphdb/sparql.py
vgraphdb-0.1.3.dist-info/LICENSE
vgraphdb-0.1.3.dist-info/METADATA
vgraphdb-0.1.3.dist-info/WHEEL
vgraphdb-0.1.3.dist-info/RECORD
