Metadata-Version: 2.3
Name: vgraphdb
Version: 0.1.3
Summary: An extension package for vectorized operations over graph databases.
License: MIT
Author: Shane H.M.
Requires-Python: >=3.9
Classifier: License :: OSI Approved :: MIT License
Classifier: Programming Language :: Python :: 3
Classifier: Programming Language :: Python :: 3.9
Classifier: Programming Language :: Python :: 3.10
Classifier: Programming Language :: Python :: 3.11
Classifier: Programming Language :: Python :: 3.12
Classifier: Programming Language :: Python :: 3.13
Requires-Dist: scikit-learn (>=1.0.0)
Requires-Dist: torch (>=1.9.0)
